Metadata-Version: 1.0
Name: tmp-binomial-gaussian-dist
Version: 0.1
Summary: Binomial and Gaussian distributions
Home-page: UNKNOWN
Author: saberny
Author-email: UNKNOWN
License: UNKNOWN
Platform: UNKNOWN
